{"YCtB/KhpVR+Elw/Xa3ut7A==":"mbr-96x64.jpg","9OZOvbXg2gM+vxoCqkNVUw==":"mbr-144x96.jpg","XmTf72yCQQAWonDL3qBp7A==":"studienkollegfes-212x123.jpg","h0QrB6nq3yNMTD7YE6s4Qw==":"studienkollegfes-1-212x123.jpg","4e61rggCmcOuhb5Y9t4XJg==":"mbr-1920x1281.jpg","ZLzlTntEcDigPAIjurjrfw==":"mbr-1920x1440.jpg","ViiYyUUDwAi1btTfMabXtw==":"mbr-1920x1239.jpg","1LscJTxyf2ubBeI68T+20g==":"mbr-1920x1079.jpg","SYgYhIwUwrDY8Nopj/Rodg==":"mbr-436x291.jpg","puy/bTMElJ1czGh75Y7XIA==":"mbr-436x290.jpg","+dcrtNpTPNC7OBl414+bAw==":"studienkollegfes-192x111.jpg","iO+oqeogDMttY0PPhlCGEg==":"logo-246x143.jpg","QDNcHa0Ka4ifFaI2NG1emQ==":"logo-1-246x143.jpg","KSMRgVMKg6b4Z2vTHeA0Tw==":"logo-2-246x143.jpg","wu0NaW4b+c0k1KpG2kEbJA==":"logo-3-246x143.jpg","S/4PwAxbPvc/vuwsovI41g==":"logo-332x192.jpg"}